{
    "projectId": "rbn9m8",
    "baseUrl": "http://degital-examination.test",
    "chromeWebSecurity": false,
    "retries": 0,
    "defaultCommandTimeout": 5000,
    "watchForFileChanges": false,
    "integrationFolder": "tests/cypress\\integration",
    "pluginsFile": "tests/cypress\\plugins/index.js",
    "videosFolder": "tests/cypress\\videos",
    "supportFile": "tests/cypress\\support/index.js",
    "screenshotsFolder": "tests/cypress\\screenshots",
    "fixturesFolder": "tests/cypress\\fixture"
}
